generic_camunda_client/__init__.py
generic_camunda_client/api_client.py
generic_camunda_client/configuration.py
generic_camunda_client/exceptions.py
generic_camunda_client/rest.py
generic_camunda_client/api/__init__.py
generic_camunda_client/api/authorization_api.py
generic_camunda_client/api/batch_api.py
generic_camunda_client/api/condition_api.py
generic_camunda_client/api/decision_definition_api.py
generic_camunda_client/api/decision_requirements_definition_api.py
generic_camunda_client/api/deployment_api.py
generic_camunda_client/api/engine_api.py
generic_camunda_client/api/event_subscription_api.py
generic_camunda_client/api/execution_api.py
generic_camunda_client/api/external_task_api.py
generic_camunda_client/api/filter_api.py
generic_camunda_client/api/group_api.py
generic_camunda_client/api/historic_activity_instance_api.py
generic_camunda_client/api/historic_batch_api.py
generic_camunda_client/api/historic_decision_definition_api.py
generic_camunda_client/api/historic_decision_instance_api.py
generic_camunda_client/api/historic_decision_requirements_definition_api.py
generic_camunda_client/api/historic_detail_api.py
generic_camunda_client/api/historic_external_task_log_api.py
generic_camunda_client/api/historic_identity_link_log_api.py
generic_camunda_client/api/historic_incident_api.py
generic_camunda_client/api/historic_job_log_api.py
generic_camunda_client/api/historic_process_definition_api.py
generic_camunda_client/api/historic_process_instance_api.py
generic_camunda_client/api/historic_task_instance_api.py
generic_camunda_client/api/historic_user_operation_log_api.py
generic_camunda_client/api/historic_variable_instance_api.py
generic_camunda_client/api/history_cleanup_api.py
generic_camunda_client/api/identity_api.py
generic_camunda_client/api/incident_api.py
generic_camunda_client/api/job_api.py
generic_camunda_client/api/job_definition_api.py
generic_camunda_client/api/message_api.py
generic_camunda_client/api/metrics_api.py
generic_camunda_client-7.18.0.dist-info/METADATA
generic_camunda_client-7.18.0.dist-info/WHEEL
generic_camunda_client-7.18.0.dist-info/top_level.txt
generic_camunda_client-7.18.0.dist-info/RECORD
